Workbook

Sheet Football
A1: Football
A3: Surname | B3: First Name | C3: Gender | D3: Parent's Name | E3: Date of Birth (dd/mm/yr) | F3: Address | G3: Contact Information | H3: Uniform Size | I3: Sport | J3: Registration Cost(US) | K3: Method Of Payment | L3: Grand Total(TT)
A4: Franklin | B4: Aurora | C4: Female | D4: Kyle Aurora | E4: =RANDBETWEEN(DATE(2007,1,1),DATE(2007,12,31)) -> 39109 | F4: 19 Mucurapo Road | G4: 1868-345-9453 | H4: Large | I4: Football | J4: =IF(I4="Football","$120",IF(I4="Basketball","$200",IF(I4="Netball","$225",IF(I4="Hockey","$275",IF(I4="Swimming","$350"))))) -> $120 | K4: Installment | L4: =IF(K4="Full",J4*Dataset!$D$3*0.9,IF(K4="Installment",J4*Dataset!$D$3*1.15)) -> 1104
A5: Maharaj | B5: Kaitlyn | C5: Female | D5: Jeremy Maharaj | E5: =RANDBETWEEN(DATE(2007,1,1),DATE(2007,12,31)) -> 39350 | F5: Constance Street | G5: 1868-224-8843 | H5: Medium | I5: Football | J5: =IF(I5="Football","$120",IF(I5="Basketball","$200",IF(I5="Netball","$225",IF(I5="Hockey","$275",IF(I5="Swimming","$350"))))) -> $120 | K5: Installment | L5: =IF(K5="Full",J5*Dataset!$D$3*0.9,IF(K5="Installment",J5*Dataset!$D$3*1.15)) -> 1104
A6: Ramousar | B6: Nathan | C6: Male | D6: Cary Ramousar | E6: =RANDBETWEEN(DATE(2007,1,1),DATE(2007,12,31)) -> 39100 | F6: 34 Carrington Street | G6: 1868-223-0012 | H6: Small | I6: Football | J6: =IF(I6="Football","$120",IF(I6="Basketball","$200",IF(I6="Netball","$225",IF(I6="Hockey","$275",IF(I6="Swimming","$350"))))) -> $120 | K6: Installment | L6: =IF(K6="Full",J6*Dataset!$D$3*0.9,IF(K6="Installment",J6*Dataset!$D$3*1.15)) -> 1104
A7: Joseph | B7: Peter | C7: Male | D7: Michael Joseph | E7: =RANDBETWEEN(DATE(2007,1,1),DATE(2007,12,31)) -> 39444 | F7: 135 John Street | G7: 1868-432-4567 | H7: Large | I7: Football | J7: =IF(I7="Football","$120",IF(I7="Basketball","$200",IF(I7="Netball","$225",IF(I7="Hockey","$275",IF(I7="Swimming","$350"))))) -> $120 | K7: Installment | L7: =IF(K7="Full",J7*Dataset!$D$3*0.9,IF(K7="Installment",J7*Dataset!$D$3*1.15)) -> 1104
A8: Sharma | B8: Andrea | C8: Female | D8: Alex Sharma | E8: =RANDBETWEEN(DATE(2007,1,1),DATE(2007,12,31)) -> 39164 | F8: #49 Thompson Street | G8: 1868-349-9732 | H8: Samll | I8: Football | J8: =IF(I8="Football","$120",IF(I8="Basketball","$200",IF(I8="Netball","$225",IF(I8="Hockey","$275",IF(I8="Swimming","$350"))))) -> $120 | K8: Installment | L8: =IF(K8="Full",J8*Dataset!$D$3*0.9,IF(K8="Installment",J8*Dataset!$D$3*1.15)) -> 1104
A9: Andrews | B9: Frank | C9: Male | D9: Kelly Andrews | E9: =RANDBETWEEN(DATE(2007,1,1),DATE(2007,12,31)) -> 39110 | F9: Lord's Street,Port of Spain | G9: 1868-783-4732 | H9: Small | I9: Football | J9: =IF(I9="Football","$120",IF(I9="Basketball","$200",IF(I9="Netball","$225",IF(I9="Hockey","$275",IF(I9="Swimming","$350"))))) -> $120 | K9: Installment | L9: =IF(K9="Full",J9*Dataset!$D$3*0.9,IF(K9="Installment",J9*Dataset!$D$3*1.15)) -> 1104
A10: Best | B10: Pauline | C10: Female | D10: Carl Best | E10: =RANDBETWEEN(DATE(2007,1,1),DATE(2007,12,31)) -> 39345 | F10: 9776 Birchpond St. | G10: 1868-745-0923 | H10: Small | I10: Football | J10: =IF(I10="Football","$120",IF(I10="Basketball","$200",IF(I10="Netball","$225",IF(I10="Hockey","$275",IF(I10="Swimming","$350"))))) -> $120 | K10: Full | L10: =IF(K10="Full",J10*Dataset!$D$3*0.9,IF(K10="Installment",J10*Dataset!$D$3*1.15)) -> 864
A11: Alvarado | B11: Elroy | C11: Male | D11: Michelle Alvarado | E11: =RANDBETWEEN(DATE(2007,1,1),DATE(2007,12,31)) -> 39098 | F11: Stone & Charles Sts., Port of Spain | G11: 1868-236-7908 | H11: Large | I11: Football | J11: =IF(I11="Football","$120",IF(I11="Basketball","$200",IF(I11="Netball","$225",IF(I11="Hockey","$275",IF(I11="Swimming","$350"))))) -> $120 | K11: Full | L11: =IF(K11="Full",J11*Dataset!$D$3*0.9,IF(K11="Installment",J11*Dataset!$D$3*1.15)) -> 864
A12: Moses | B12: Maurice | C12: Female | D12: Andrea Moses | E12: =RANDBETWEEN(DATE(2007,1,1),DATE(2007,12,31)) -> 39435 | F12: 102 Nolan Street | G12: 1868-456-3722 | H12: Small | I12: Football | J12: =IF(I12="Football","$120",IF(I12="Basketball","$200",IF(I12="Netball","$225",IF(I12="Hockey","$275",IF(I12="Swimming","$350"))))) -> $120 | K12: Full | L12: =IF(K12="Full",J12*Dataset!$D$3*0.9,IF(K12="Installment",J12*Dataset!$D$3*1.15)) -> 864
A13: Jamieson | B13: Richard | C13: Male | D13: Daisy Jamieson | E13: =RANDBETWEEN(DATE(2007,1,1),DATE(2007,12,31)) -> 39383 | F13: Milford Road, Milford | G13: 1868-745-9021 | H13: Medium | I13: Football | J13: =IF(I13="Football","$120",IF(I13="Basketball","$200",IF(I13="Netball","$225",IF(I13="Hockey","$275",IF(I13="Swimming","$350"))))) -> $120 | K13: Full | L13: =IF(K13="Full",J13*Dataset!$D$3*0.9,IF(K13="Installment",J13*Dataset!$D$3*1.15)) -> 864
A14: Jamieson | B14: Mark | C14: Male | D14: Daisy Jamieson | E14: =RANDBETWEEN(DATE(2007,1,1),DATE(2007,12,31)) -> 39106 | F14: Milford Road, Milford | G14: 1868-745-9021 | H14: Medium | I14: Football | J14: =IF(I14="Football","$120",IF(I14="Basketball","$200",IF(I14="Netball","$225",IF(I14="Hockey","$275",IF(I14="Swimming","$350"))))) -> $120 | K14: Full | L14: =IF(K14="Full",J14*Dataset!$D$3*0.9,IF(K14="Installment",J14*Dataset!$D$3*1.15)) -> 864
A15: Rosa | B15: Susan | C15: Female | D15: Natasha Rosa | E15: =RANDBETWEEN(DATE(2007,1,1),DATE(2007,12,31)) -> 39198 | F15: 22 Penco Street | G15: 1868-275-9743 | H15: Medium | I15: Football | J15: =IF(I15="Football","$120",IF(I15="Basketball","$200",IF(I15="Netball","$225",IF(I15="Hockey","$275",IF(I15="Swimming","$350"))))) -> $120 | K15: Full | L15: =IF(K15="Full",J15*Dataset!$D$3*0.9,IF(K15="Installment",J15*Dataset!$D$3*1.15)) -> 864
... A18: Serelo | B18: David | C18: Male | D18: Kevin Serelo | E18: =RANDBETWEEN(DATE(2007,1,1),DATE(2007,12,31)) -> 39225 | F18: 15 Woodpecker Lane, P.O.Box 23700 | G18: 1868-321-7832 | H18: Large | I18: Football | J18: =IF(I18="Football","$120",IF(I18="Basketball","$200",IF(I18="Netball","$225",IF(I18="Hockey","$275",IF(I18="Swimming","$350"))))) -> $120 | K18: Full | L18: =IF(K18="Full",J18*Dataset!$D$3*0.9,IF(K18="Installment",J18*Dataset!$D$3*1.15)) -> 864
K19: Total | L19: =SUM(L4:L18) -> 14400
H20: Number of Campers | I20: =COUNTA(A4:A18) -> 15

Sheet Basketball
A1: Basketball
A2: Surname | B2: First Name | C2: Gender | D2: Parent's Name | E2: Date of Birth (dd/mm/yr) | F2: Address | G2: Contact Information | H2: Uniform Size | I2: Sport | J2: Registration Cost | K2: Method Of Payment | L2: Grand Total(TT)
A3: Wilson | B3: Nina | C3: Female | D3: Carolyn Wilson | E3: =RANDBETWEEN(DATE(2007,1,1),DATE(2007,12,31)) -> 39110 | F3: Store Bay Road, Store Bay | G3: 1868-432-1738 | H3: Medium | I3: Basketball | J3: =IF(I3="Football","$120",IF(I3="Basketball","$200",IF(I3="Netball","$225",IF(I3="Hockey","$275",IF(I3="Swimming","$350"))))) -> $200 | K3: Full | L3: =IF(K4="Full",J4*Dataset!$D$3*0.9,IF(K4="Installment",J4*Dataset!$D$3*1.15)) -> 1840
A4: Mohammed | B4: Varen | C4: Male | D4: Siraj Mohammed | E4: =RANDBETWEEN(DATE(2007,1,1),DATE(2007,12,31)) -> 39267 | F4: 7 Benares Street | G4: 1868-213-4832 | H4: Medium | I4: Basketball | J4: =IF(I4="Football","$120",IF(I4="Basketball","$200",IF(I4="Netball","$225",IF(I4="Hockey","$275",IF(I4="Swimming","$350"))))) -> $200 | K4: Installment | L4: =IF(K5="Full",J5*Dataset!$D$3*0.9,IF(K5="Installment",J5*Dataset!$D$3*1.15)) -> 1440
A5: Charles | B5: Weasley | C5: Male | D5: Matthew Charles | E5: =RANDBETWEEN(DATE(2007,1,1),DATE(2007,12,31)) -> 39382 | F5: St.Mary's Village | G5: 1868-453-0983 | H5: Large | I5: Basketball | J5: =IF(I5="Football","$120",IF(I5="Basketball","$200",IF(I5="Netball","$225",IF(I5="Hockey","$275",IF(I5="Swimming","$350"))))) -> $200 | K5: Full | L5: =IF(K6="Full",J6*Dataset!$D$3*0.9,IF(K6="Installment",J6*Dataset!$D$3*1.15)) -> 1840
A6: Pierra | B6: Naomi | C6: Female | D6: Natalie Pierra | E6: =RANDBETWEEN(DATE(2007,1,1),DATE(2007,12,31)) -> 39154 | F6: Main Street | G6: 1868-463-8291 | H6: Small | I6: Basketball | J6: =IF(I6="Football","$120",IF(I6="Basketball","$200",IF(I6="Netball","$225",IF(I6="Hockey","$275",IF(I6="Swimming","$350"))))) -> $200 | K6: Installment | L6: =IF(K7="Full",J7*Dataset!$D$3*0.9,IF(K7="Installment",J7*Dataset!$D$3*1.15)) -> 1440
A7: James | B7: Susan | C7: Female | D7: Dale James | E7: =RANDBETWEEN(DATE(2007,1,1),DATE(2007,12,31)) -> 39191 | F7: 5a Lazare Street,Chaguanas,Trinidad and Tobago | G7: 1868-463-2881 | H7: Large | I7: Basketball | J7: =IF(I7="Football","$120",IF(I7="Basketball","$200",IF(I7="Netball","$225",IF(I7="Hockey","$275",IF(I7="Swimming","$350"))))) -> $200 | K7: Full | L7: =IF(K8="Full",J8*Dataset!$D$3*0.9,IF(K8="Installment",J8*Dataset!$D$3*1.15)) -> 1440
A8: Chan | B8: Kevin | C8: Male | D8: Hitashi Chan | E8: =RANDBETWEEN(DATE(2007,1,1),DATE(2007,12,31)) -> 39189 | F8: Lp# 2 Nicholas St Morne Coco Rd ,Arima,Trinidad and Tobago | G8: 1868-388-3728 | H8: Medium | I8: Basketball | J8: =IF(I8="Football","$120",IF(I8="Basketball","$200",IF(I8="Netball","$225",IF(I8="Hockey","$275",IF(I8="Swimming","$350"))))) -> $200 | K8: Full | L8: =IF(K9="Full",J9*Dataset!$D$3*0.9,IF(K9="Installment",J9*Dataset!$D$3*1.15)) -> 1440
A9: Nord | B9: Christ | C9: Male | D9: Eliana Nord | E9: =RANDBETWEEN(DATE(2007,1,1),DATE(2007,12,31)) -> 39384 | F9: 63 Eastern Main Road | G9: 1868-547-3422 | H9: Small | I9: Basketball | J9: =IF(I9="Football","$120",IF(I9="Basketball","$200",IF(I9="Netball","$225",IF(I9="Hockey","$275",IF(I9="Swimming","$350"))))) -> $200 | K9: Full | L9: =IF(K10="Full",J10*Dataset!$D$3*0.9,IF(K10="Installment",J10*Dataset!$D$3*1.15)) -> 1840
A10: Stuart | B10: Aslan | C10: Male | D10: Desha Stuart | E10: =RANDBETWEEN(DATE(2007,1,1),DATE(2007,12,31)) -> 39176 | F10: Breeze Hall Mall | G10: 1868-342-2183 | H10: Small | I10: Basketball | J10: =IF(I10="Football","$120",IF(I10="Basketball","$200",IF(I10="Netball","$225",IF(I10="Hockey","$275",IF(I10="Swimming","$350"))))) -> $200 | K10: Installment | L10: =IF(K11="Full",J11*Dataset!$D$3*0.9,IF(K11="Installment",J11*Dataset!$D$3*1.15)) -> 1840
A11: Ali | B11: Adrian | C11: Male | D11: Ishan Ali | E11: =RANDBETWEEN(DATE(2007,1,1),DATE(2007,12,31)) -> 39180 | F11: 1-5 Princess Margaret Street, P.O.Box 13800 | G11: 1868-928-2321 | H11: Medium | I11: Basketball | J11: =IF(I11="Football","$120",IF(I11="Basketball","$200",IF(I11="Netball","$225",IF(I11="Hockey","$275",IF(I11="Swimming","$350"))))) -> $200 | K11: Installment | L11: =IF(K12="Full",J12*Dataset!$D$3*0.9,IF(K12="Installment",J12*Dataset!$D$3*1.15)) -> 1440
A12: Lewis | B12: Maria | C12: Female | D12: Mia Lewis | E12: =RANDBETWEEN(DATE(2007,1,1),DATE(2007,12,31)) -> 39098 | F12: 15 Zimbabwe Lane | G12: 1868-736-3982 | H12: Small | I12: Basketball | J12: =IF(I12="Football","$120",IF(I12="Basketball","$200",IF(I12="Netball","$225",IF(I12="Hockey","$275",IF(I12="Swimming","$350"))))) -> $200 | K12: Full | L12: =IF(K13="Full",J13*Dataset!$D$3*0.9,IF(K13="Installment",J13*Dataset!$D$3*1.15)) -> 1440
A13: Seepersaud | B13: Darell | C13: Male | D13: Aisha Seepersaud | E13: =RANDBETWEEN(DATE(2007,1,1),DATE(2007,12,31)) -> 39194 | F13: Bacolet Street | G13: 1868-437-2928 | H13: Large | I13: Basketball | J13: =IF(I13="Football","$120",IF(I13="Basketball","$200",IF(I13="Netball","$225",IF(I13="Hockey","$275",IF(I13="Swimming","$350"))))) -> $200 | K13: Full | L13: =IF(K14="Full",J14*Dataset!$D$3*0.9,IF(K14="Installment",J14*Dataset!$D$3*1.15)) -> 1840
A14: Sylvester | B14: Daren | C14: Male | D14: Kimberly Sylvester | E14: =RANDBETWEEN(DATE(2007,1,1),DATE(2007,12,31)) -> 39351 | F14: 130 Seventh Street Barataria ,Chaguanas,Trinidad and Tobago | G14: 1868-477-2372 | H14: Medium | I14: Basketball | J14: =IF(I14="Football","$120",IF(I14="Basketball","$200",IF(I14="Netball","$225",IF(I14="Hockey","$275",IF(I14="Swimming","$350"))))) -> $200 | K14: Installment | L14: =IF(K15="Full",J15*Dataset!$D$3*0.9,IF(K15="Installment",J15*Dataset!$D$3*1.15)) -> 1440
... A16: Nepaul | B16: Shilah | C16: Female | D16: Hawi Nepaul | E16: =RANDBETWEEN(DATE(2007,1,1),DATE(2007,12,31)) -> 39410 | F16: 23 Prime Road St., Chaguanas | G16: 1868-309-9392 | H16: Small | I16: Basketball | J16: =IF(I16="Football","$120",IF(I16="Basketball","$200",IF(I16="Netball","$225",IF(I16="Hockey","$275",IF(I16="Swimming","$350"))))) -> $200 | K16: Installment | L16: =IF(K17="Full",J17*Dataset!$D$3*0.9,IF(K17="Installment",J17*Dataset!$D$3*1.15)) -> 1440
A17: Apple | B17: Joey | C17: Male | D17: Nia Apple | E17: =RANDBETWEEN(DATE(2007,1,1),DATE(2007,12,31)) -> 39128 | F17: 37 Tragarete Road,Arima,Trinidad and Tobago | G17: 1868-381-3883 | H17: Medium | I17: Basketball | J17: =IF(I17="Football","$120",IF(I17="Basketball","$200",IF(I17="Netball","$225",IF(I17="Hockey","$275",IF(I17="Swimming","$350"))))) -> $200 | K17: Full | L17: =IF(K17="Full",J17*Dataset!$D$3*0.9,IF(K17="Installment",J17*Dataset!$D$3*1.15)) -> 1440
K18: Total | L18: =SUM(L3:L17) -> 24000
H19: Number of Campers | I19: =COUNTA(A3:A17) -> 15

Sheet Netball
A1: Netball
A2: Surname | B2: First Name | C2: Gender | D2: Parent's Name | E2: Date of Birth (dd/mm/yr) | F2: Address | G2: Contact Information | H2: Uniform Size | I2: Sport | J2: Registration Cost | K2: Method Of Payment | L2: Grand Total(TT)
A3: James | B3: Cassidy | C3: Female | D3: Andrey James | E3: =RANDBETWEEN(DATE(2007,1,1),DATE(2007,12,31)) -> 39322 | F3: 3A Silvermill San Juan,Diego Martin,Trinidad and Tobago | G3: 1868-462-7238 | H3: Large | I3: Netball | J3: =IF(I3="Football","$120",IF(I3="Basketball","$200",IF(I3="Netball","$225",IF(I3="Hockey","$275",IF(I3="Swimming","$350"))))) -> $225 | K3: Installment | L3: =IF(K3="Full",J3*Dataset!$D$3*0.9,IF(K3="Installment",J3*Dataset!$D$3*1.15)) -> 2070
A4: Anderson | B4: Julie | C4: Female | D4: Zane Anderson | E4: =RANDBETWEEN(DATE(2007,1,1),DATE(2007,12,31)) -> 39280 | F4: Bhagoutie Trace San Juan,Diego Martin,Trinidad and Tobago | G4: 1868-472-3828 | H4: Medium | I4: Netball | J4: =IF(I4="Football","$120",IF(I4="Basketball","$200",IF(I4="Netball","$225",IF(I4="Hockey","$275",IF(I4="Swimming","$350"))))) -> $225 | K4: Installment | L4: =IF(K4="Full",J4*Dataset!$D$3*0.9,IF(K4="Installment",J4*Dataset!$D$3*1.15)) -> 2070
A5: Ramlogan | B5: Arun | C5: Male | D5: Bridgette Ramlogan | E5: =RANDBETWEEN(DATE(2007,1,1),DATE(2007,12,31)) -> 39137 | F5: 10-16 Lady Hailes Avenue ,Marabella,Trinidad and Tobago | G5: 1868-348-3881 | H5: Medium | I5: Netball | J5: =IF(I5="Football","$120",IF(I5="Basketball","$200",IF(I5="Netball","$225",IF(I5="Hockey","$275",IF(I5="Swimming","$350"))))) -> $225 | K5: Installment | L5: =IF(K5="Full",J5*Dataset!$D$3*0.9,IF(K5="Installment",J5*Dataset!$D$3*1.15)) -> 2070
A6: Lisa | B6: Alejandro | C6: Male | D6: Ferdinand Lisa | E6: =RANDBETWEEN(DATE(2007,1,1),DATE(2007,12,31)) -> 39413 | F6: 74 Ana St. Woodbrook ,Marabella,Trinidad and Tobago | G6: 1868-489-0482 | H6: Large | I6: Netball | J6: =IF(I6="Football","$120",IF(I6="Basketball","$200",IF(I6="Netball","$225",IF(I6="Hockey","$275",IF(I6="Swimming","$350"))))) -> $225 | K6: Installment | L6: =IF(K6="Full",J6*Dataset!$D$3*0.9,IF(K6="Installment",J6*Dataset!$D$3*1.15)) -> 2070
A7: Ross | B7: Harvey | C7: Male | D7: Victoria Ross | E7: =RANDBETWEEN(DATE(2007,1,1),DATE(2007,12,31)) -> 39140 | F7: Western Main Road,Port of Spain,Trinidad and Tobago | G7: 1868-489-4922 | H7: Medium | I7: Netball | J7: =IF(I7="Football","$120",IF(I7="Basketball","$200",IF(I7="Netball","$225",IF(I7="Hockey","$275",IF(I7="Swimming","$350"))))) -> $225 | K7: Installment | L7: =IF(K7="Full",J7*Dataset!$D$3*0.9,IF(K7="Installment",J7*Dataset!$D$3*1.15)) -> 2070
A8: Putlin | B8: Sarah | C8: Female | D8: Ameera Putlin | E8: =RANDBETWEEN(DATE(2007,1,1),DATE(2007,12,31)) -> 39313 | F8: 130 Seventh Street Barataria ,Arima,Trinidad and Tobago | G8: 1868-283-3821 | H8: Small | I8: Netball | J8: =IF(I8="Football","$120",IF(I8="Basketball","$200",IF(I8="Netball","$225",IF(I8="Hockey","$275",IF(I8="Swimming","$350"))))) -> $225 | K8: Full | L8: =IF(K8="Full",J8*Dataset!$D$3*0.9,IF(K8="Installment",J8*Dataset!$D$3*1.15)) -> 1620
A9: Armstrong | B9: Clyde | C9: Male | D9: Zoe Armstrong | E9: =RANDBETWEEN(DATE(2007,1,1),DATE(2007,12,31)) -> 39257 | F9: 16 Real Street San Juan,Diego Martin,Trinidad and Tobago | G9: 1868-389-3742 | H9: Medium | I9: Netball | J9: =IF(I9="Football","$120",IF(I9="Basketball","$200",IF(I9="Netball","$225",IF(I9="Hockey","$275",IF(I9="Swimming","$350"))))) -> $225 | K9: Full | L9: =IF(K9="Full",J9*Dataset!$D$3*0.9,IF(K9="Installment",J9*Dataset!$D$3*1.15)) -> 1620
A10: Okaniku | B10: Sasa | C10: Female | D10: Leroy Okaniku | E10: =RANDBETWEEN(DATE(2007,1,1),DATE(2007,12,31)) -> 39229 | F10: 70 Woodford St,Diego Martin,Trinidad and Tobago | G10: 1868-244-4839 | H10: Samll | I10: Netball | J10: =IF(I10="Football","$120",IF(I10="Basketball","$200",IF(I10="Netball","$225",IF(I10="Hockey","$275",IF(I10="Swimming","$350"))))) -> $225 | K10: Full | L10: =IF(K10="Full",J10*Dataset!$D$3*0.9,IF(K10="Installment",J10*Dataset!$D$3*1.15)) -> 1620
A11: Mathews | B11: Werly | C11: Female | D11: Shaun Matthews | E11: =RANDBETWEEN(DATE(2007,1,1),DATE(2007,12,31)) -> 39163 | F11: 19 Papourie Road ,Marabella,Trinidad and Tobago | G11: 1868-841-8894 | H11: Small | I11: Netball | J11: =IF(I11="Football","$120",IF(I11="Basketball","$200",IF(I11="Netball","$225",IF(I11="Hockey","$275",IF(I11="Swimming","$350"))))) -> $225 | K11: Full | L11: =IF(K11="Full",J11*Dataset!$D$3*0.9,IF(K11="Installment",J11*Dataset!$D$3*1.15)) -> 1620
A12: Fokina | B12: Miguel | C12: Male | D12: Ronaldo Fokina | E12: =RANDBETWEEN(DATE(2007,1,1),DATE(2007,12,31)) -> 39382 | F12: Camden Road. Camden House ,Port of Spain,Trinidad and Tobago | G12: 1868-444-4843 | H12: Medium | I12: Netball | J12: =IF(I12="Football","$120",IF(I12="Basketball","$200",IF(I12="Netball","$225",IF(I12="Hockey","$275",IF(I12="Swimming","$350"))))) -> $225 | K12: Full | L12: =IF(K12="Full",J12*Dataset!$D$3*0.9,IF(K12="Installment",J12*Dataset!$D$3*1.15)) -> 1620
A13: Morilla | B13: Christien | C13: Female | D13: Jon Morilla | E13: =RANDBETWEEN(DATE(2007,1,1),DATE(2007,12,31)) -> 39224 | F13: 13 Buller St Woodbrook,Port of Spain,Trinidad and Tobago | G13: 1868-756-3982 | H13: Small | I13: Netball | J13: =IF(I13="Football","$120",IF(I13="Basketball","$200",IF(I13="Netball","$225",IF(I13="Hockey","$275",IF(I13="Swimming","$350"))))) -> $225 | K13: Full | L13: =IF(K13="Full",J13*Dataset!$D$3*0.9,IF(K13="Installment",J13*Dataset!$D$3*1.15)) -> 1620
A14: Gum | B14: Rice | C14: Male | D14: Kim Rice | E14: =RANDBETWEEN(DATE(2007,1,1),DATE(2007,12,31)) -> 39132 | F14: 17 Levern St. Diego Martin, Port of Spain | G14: 1868-938-3722 | H14: Large | I14: Netball | J14: =IF(I14="Football","$120",IF(I14="Basketball","$200",IF(I14="Netball","$225",IF(I14="Hockey","$275",IF(I14="Swimming","$350"))))) -> $225 | K14: Full | L14: =IF(K14="Full",J14*Dataset!$D$3*0.9,IF(K14="Installment",J14*Dataset!$D$3*1.15)) -> 1620
A15: Sealy | B15: Larry | C15: Male | D15: Drew Sealy | E15: =RANDBETWEEN(DATE(2007,1,1),DATE(2007,12,31)) -> 39391 | F15: Cocorite,Port of Spain,Trinidad and Tobago | G15: 1868-437-1928 | H15: Large | I15: Netball | J15: =IF(I15="Football","$120",IF(I15="Basketball","$200",IF(I15="Netball","$225",IF(I15="Hockey","$275",IF(I15="Swimming","$350"))))) -> $225 | K15: Full | L15: =IF(K15="Full",J15*Dataset!$D$3*0.9,IF(K15="Installment",J15*Dataset!$D$3*1.15)) -> 1620
K16: Total | L16: =SUM(L3:L15) -> 23310
H17: Number of Campers | I17: =COUNTA(A3:A15) -> 13

Sheet Hockey
A1: Hockey
A2: Surname | B2: First Name | C2: Gender | D2: Parent's Name | E2: Date of Birth (dd/mm/yr) | F2: Address | G2: Contact Information | H2: Uniform Size | I2: Sport | J2: Registration Cost | K2: Method Of Payment | L2: Grand Total(TT)
A3: Tomoko | B3: Nadine | C3: Female | D3: Carrol Tomoko | E3: =RANDBETWEEN(DATE(2007,1,1),DATE(2007,12,31)) -> 39391 | F3: School Street ,Point Fortin,Trinidad and Tobago | G3: 1868-474-2372 | H3: Medium | I3: Hockey | J3: =IF(I3="Football","$120",IF(I3="Basketball","$200",IF(I3="Netball","$225",IF(I3="Hockey","$275",IF(I3="Swimming","$350"))))) -> $275 | K3: Installment | L3: =IF(K4="Full",J4*Dataset!$D$3*0.9,IF(K4="Installment",J4*Dataset!$D$3*1.15)) -> 2530
A4: Alex | B4: Graig | C4: Male | D4: Mario Alex | E4: =RANDBETWEEN(DATE(2007,1,1),DATE(2007,12,31)) -> 39380 | F4: 37 Tragarete Road,Point Fortin,Trinidad and Tobago | G4: 1868-237-3926 | H4: Small | I4: Hockey | J4: =IF(I4="Football","$120",IF(I4="Basketball","$200",IF(I4="Netball","$225",IF(I4="Hockey","$275",IF(I4="Swimming","$350"))))) -> $275 | K4: Installment | L4: =IF(K5="Full",J5*Dataset!$D$3*0.9,IF(K5="Installment",J5*Dataset!$D$3*1.15)) -> 1980
A5: Wilhemina | B5: Elna | C5: Female | D5: Rod Wilhemina | E5: =RANDBETWEEN(DATE(2007,1,1),DATE(2007,12,31)) -> 39407 | F5: Union Hall ,San Fernando,Trinidad and Tobago | G5: 1868-283-3832 | H5: Medium | I5: Hockey | J5: =IF(I5="Football","$120",IF(I5="Basketball","$200",IF(I5="Netball","$225",IF(I5="Hockey","$275",IF(I5="Swimming","$350"))))) -> $275 | K5: Full | L5: =IF(K6="Full",J6*Dataset!$D$3*0.9,IF(K6="Installment",J6*Dataset!$D$3*1.15)) -> 2530
A6: Floretta | B6: Louisa | C6: Female | D6: Dawna Floretta | E6: =RANDBETWEEN(DATE(2007,1,1),DATE(2007,12,31)) -> 39340 | F6: 64 Eligon Ave ,Tunapuna,Trinidad and Tobago | G6: 1868-462-7231 | H6: Small | I6: Hockey | J6: =IF(I6="Football","$120",IF(I6="Basketball","$200",IF(I6="Netball","$225",IF(I6="Hockey","$275",IF(I6="Swimming","$350"))))) -> $275 | K6: Installment | L6: =IF(K7="Full",J7*Dataset!$D$3*0.9,IF(K7="Installment",J7*Dataset!$D$3*1.15)) -> 1980
A7: Shalonda | B7: Lisabeth | C7: Female | D7: Shawanda Shalonda | E7: =RANDBETWEEN(DATE(2007,1,1),DATE(2007,12,31)) -> 39122 | F7: Beckles Lane and Eastern Main Road ,Tunapuna,Trinidad and Tobago | G7: 1868-244-4832 | H7: Medium | I7: Hockey | J7: =IF(I7="Football","$120",IF(I7="Basketball","$200",IF(I7="Netball","$225",IF(I7="Hockey","$275",IF(I7="Swimming","$350"))))) -> $275 | K7: Full | L7: =IF(K8="Full",J8*Dataset!$D$3*0.9,IF(K8="Installment",J8*Dataset!$D$3*1.15)) -> 2530
A8: Burt | B8: Amada | C8: Female | D8: Sofia Burt | E8: =RANDBETWEEN(DATE(2007,1,1),DATE(2007,12,31)) -> 39195 | F8: Sam Boucaud Rd. Upr S/Cruz ,Tunapuna,Trinidad and Tobago | G8: 1868-472-6828 | H8: Small | I8: Hockey | J8: =IF(I8="Football","$120",IF(I8="Basketball","$200",IF(I8="Netball","$225",IF(I8="Hockey","$275",IF(I8="Swimming","$350"))))) -> $275 | K8: Installment | L8: =IF(K9="Full",J9*Dataset!$D$3*0.9,IF(K9="Installment",J9*Dataset!$D$3*1.15)) -> 2530
A9: Zoe | B9: Isaias | C9: Male | D9: Shirlee Zoe | E9: =RANDBETWEEN(DATE(2007,1,1),DATE(2007,12,31)) -> 39265 | F9: Eastern Main Road,San Fernando,Trinidad and Tobago | G9: 1868-382-3883 | H9: Large | I9: Hockey | J9: =IF(I9="Football","$120",IF(I9="Basketball","$200",IF(I9="Netball","$225",IF(I9="Hockey","$275",IF(I9="Swimming","$350"))))) -> $275 | K9: Installment | L9: =IF(K10="Full",J10*Dataset!$D$3*0.9,IF(K10="Installment",J10*Dataset!$D$3*1.15)) -> 2530
A10: Maribeth | B10: Ona | C10: Male | D10: Inger Maribeth | E10: =RANDBETWEEN(DATE(2007,1,1),DATE(2007,12,31)) -> 39150 | F10: Fernandes Industrial Estate ,Tunapuna,Trinidad and Tobago | G10: 1868-383-3742 | H10: Small | I10: Hockey | J10: =IF(I10="Football","$120",IF(I10="Basketball","$200",IF(I10="Netball","$225",IF(I10="Hockey","$275",IF(I10="Swimming","$350"))))) -> $275 | K10: Installment | L10: =IF(K11="Full",J11*Dataset!$D$3*0.9,IF(K11="Installment",J11*Dataset!$D$3*1.15)) -> 2530
A11: Miyoko | B11: Kizzie | C11: Female | D11: Saul Miyoko | E11: =RANDBETWEEN(DATE(2007,1,1),DATE(2007,12,31)) -> 39443 | F11: Fleming St. Longdenville ,Port of Spain,Trinidad and Tobago | G11: 1868-348-3831 | H11: Medium | I11: Hockey | J11: =IF(I11="Football","$120",IF(I11="Basketball","$200",IF(I11="Netball","$225",IF(I11="Hockey","$275",IF(I11="Swimming","$350"))))) -> $275 | K11: Installment | L11: =IF(K12="Full",J12*Dataset!$D$3*0.9,IF(K12="Installment",J12*Dataset!$D$3*1.15)) -> 1980
A12: Le | B12: Elmira | C12: Female | D12: Mariel Le | E12: =RANDBETWEEN(DATE(2007,1,1),DATE(2007,12,31)) -> 39122 | F12: 6a Queen,Port of Spain,Trinidad and Tobago | G12: 1868-419-0482 | H12: Small | I12: Hockey | J12: =IF(I12="Football","$120",IF(I12="Basketball","$200",IF(I12="Netball","$225",IF(I12="Hockey","$275",IF(I12="Swimming","$350"))))) -> $275 | K12: Full | L12: =IF(K13="Full",J13*Dataset!$D$3*0.9,IF(K13="Installment",J13*Dataset!$D$3*1.15)) -> 1980
A13: William | B13: Stanford | C13: Male | D13: Echo Williams | E13: =RANDBETWEEN(DATE(2007,1,1),DATE(2007,12,31)) -> 39325 | F13: 12 Ragbir Street ,Port of Spain,Trinidad and Tobago | G13: 1868-841-8494 | H13: Large | I13: Hockey | J13: =IF(I13="Football","$120",IF(I13="Basketball","$200",IF(I13="Netball","$225",IF(I13="Hockey","$275",IF(I13="Swimming","$350"))))) -> $275 | K13: Full | L13: =IF(K14="Full",J14*Dataset!$D$3*0.9,IF(K14="Installment",J14*Dataset!$D$3*1.15)) -> 1980
A14: Lori | B14: Twila | C14: Female | D14: Robert Lori | E14: =RANDBETWEEN(DATE(2007,1,1),DATE(2007,12,31)) -> 39389 | F14: Lp# 2 Nicholas St Morne Coco Rd ,Port of Spain,Trinidad and Tobago | G14: 1868-489-4622 | H14: Large | I14: Hockey | J14: =IF(I14="Football","$120",IF(I14="Basketball","$200",IF(I14="Netball","$225",IF(I14="Hockey","$275",IF(I14="Swimming","$350"))))) -> $275 | K14: Full | L14: =IF(K14="Full",J14*Dataset!$D$3*0.9,IF(K14="Installment",J14*Dataset!$D$3*1.15)) -> 1980
K15: Total | L15: =SUM(L4:L14) -> 24530
H16: Number of Campers | I16: =COUNTA(A3:A14) -> 12

Sheet Swimming
A1: Swimming
A2: Surname | B2: First Name | C2: Gender | D2: Parent's Name | E2: Date of Birth (dd/mm/yr) | F2: Address | G2: Contact Information | H2: Uniform Size | I2: Sport | J2: Registration Cost | K2: Method Of Payment | L2: Grand Total(TT)
A3: Rena | B3: Hilda | C3: Male | D3: Krystyna Rena | E3: =RANDBETWEEN(DATE(2007,1,1),DATE(2007,12,31)) -> 39412 | F3: St Croix Road,Port of Spain,Trinidad and Tobago | G3: 1868-444-4841 | H3: Small | I3: Swimming | J3: =IF(I3="Football","$120",IF(I3="Basketball","$200",IF(I3="Netball","$225",IF(I3="Hockey","$275",IF(I3="Swimming","$350"))))) -> $350 | K3: Installment | L3: =IF(K3="Full",J3*Dataset!$D$3*0.9,IF(K3="Installment",J3*Dataset!$D$3*1.15)) -> 3220
A4: Aurora | B4: Catherine | C4: Female | D4: Caroline Aurora | E4: =RANDBETWEEN(DATE(2007,1,1),DATE(2007,12,31)) -> 39361 | F4: St. John,Port of Spain,Trinidad and Tobago | G4: 1868-745-0926 | H4: Medium | I4: Swimming | J4: =IF(I4="Football","$120",IF(I4="Basketball","$200",IF(I4="Netball","$225",IF(I4="Hockey","$275",IF(I4="Swimming","$350"))))) -> $350 | K4: Installment | L4: =IF(K4="Full",J4*Dataset!$D$3*0.9,IF(K4="Installment",J4*Dataset!$D$3*1.15)) -> 3220
A5: Twyla | B5: Hosea | C5: Female | D5: Charita Twyla | E5: =RANDBETWEEN(DATE(2007,1,1),DATE(2007,12,31)) -> 39141 | F5: Clare Street ,Port of Spain,Trinidad and Tobago | G5: 1868-345-9468 | H5: Small | I5: Swimming | J5: =IF(I5="Football","$120",IF(I5="Basketball","$200",IF(I5="Netball","$225",IF(I5="Hockey","$275",IF(I5="Swimming","$350"))))) -> $350 | K5: Installment | L5: =IF(K5="Full",J5*Dataset!$D$3*0.9,IF(K5="Installment",J5*Dataset!$D$3*1.15)) -> 3220
A6: Angelia | B6: Marty | C6: Male | D6: April Angelai | E6: =RANDBETWEEN(DATE(2007,1,1),DATE(2007,12,31)) -> 39348 | F6: Corner Richmond. London Street,Tunapuna,Trinidad and Tobago | G6: 1868-224-8443 | H6: Large | I6: Swimming | J6: =IF(I6="Football","$120",IF(I6="Basketball","$200",IF(I6="Netball","$225",IF(I6="Hockey","$275",IF(I6="Swimming","$350"))))) -> $350 | K6: Full | L6: =IF(K6="Full",J6*Dataset!$D$3*0.9,IF(K6="Installment",J6*Dataset!$D$3*1.15)) -> 2520
A7: Fernanda | B7: Elfreda | C7: Female | D7: Trinity Fernanda | E7: =RANDBETWEEN(DATE(2007,1,1),DATE(2007,12,31)) -> 39383 | F7: 22 Eleanor Street,Tunapuna,Trinidad and Tobago | G7: 1868-456-3729 | H7: Medium | I7: Swimming | J7: =IF(I7="Football","$120",IF(I7="Basketball","$200",IF(I7="Netball","$225",IF(I7="Hockey","$275",IF(I7="Swimming","$350"))))) -> $350 | K7: Full | L7: =IF(K7="Full",J7*Dataset!$D$3*0.9,IF(K7="Installment",J7*Dataset!$D$3*1.15)) -> 2520
A8: Christel | B8: Mathilde | C8: Male | D8: Gemini Christel | E8: =RANDBETWEEN(DATE(2007,1,1),DATE(2007,12,31)) -> 39379 | F8: Alexander St.,Tunapuna,Trinidad and Tobago | G8: 1868-745-9020 | H8: Small | I8: Swimming | J8: =IF(I8="Football","$120",IF(I8="Basketball","$200",IF(I8="Netball","$225",IF(I8="Hockey","$275",IF(I8="Swimming","$350"))))) -> $350 | K8: Installment | L8: =IF(K8="Full",J8*Dataset!$D$3*0.9,IF(K8="Installment",J8*Dataset!$D$3*1.15)) -> 3220
A9: Brittny | B9: Vi | C9: Male | D9: Avery Brittny | E9: =RANDBETWEEN(DATE(2007,1,1),DATE(2007,12,31)) -> 39196 | F9: 109d Coffee Street ,Tunapuna,Trinidad and Tobago | G9: 1868-755-9021 | H9: Medium | I9: Swimming | J9: =IF(I9="Football","$120",IF(I9="Basketball","$200",IF(I9="Netball","$225",IF(I9="Hockey","$275",IF(I9="Swimming","$350"))))) -> $350 | K9: Installment | L9: =IF(K9="Full",J9*Dataset!$D$3*0.9,IF(K9="Installment",J9*Dataset!$D$3*1.15)) -> 3220
A10: Darnell | B10: Patrick | C10: Male | D10: Elias Patrick | E10: =RANDBETWEEN(DATE(2007,1,1),DATE(2007,12,31)) -> 39299 | F10: 7A O'Meara Industrial Estate,Tunapuna,Trinidad and Tobago | G10: 1868-223-0013 | H10: Large | I10: Swimming | J10: =IF(I10="Football","$120",IF(I10="Basketball","$200",IF(I10="Netball","$225",IF(I10="Hockey","$275",IF(I10="Swimming","$350"))))) -> $350 | K10: Installment | L10: =IF(K10="Full",J10*Dataset!$D$3*0.9,IF(K10="Installment",J10*Dataset!$D$3*1.15)) -> 3220
A11: William | B11: Heather | C11: Female | D11: Shea William | E11: =RANDBETWEEN(DATE(2007,1,1),DATE(2007,12,31)) -> 39229 | F11: Mc Bean,Arouca,Trinidad and Tobago | G11: 1868-732-4567 | H11: Large | I11: Swimming | J11: =IF(I11="Football","$120",IF(I11="Basketball","$200",IF(I11="Netball","$225",IF(I11="Hockey","$275",IF(I11="Swimming","$350"))))) -> $350 | K11: Full | L11: =IF(K11="Full",J11*Dataset!$D$3*0.9,IF(K11="Installment",J11*Dataset!$D$3*1.15)) -> 2520
A12: Lovetta | B12: Blythe | C12: Male | D12: Connor Lovetta | E12: =RANDBETWEEN(DATE(2007,1,1),DATE(2007,12,31)) -> 39394 | F12: Shoppes of Maraval. Maraval,Arouca,Trinidad and Tobago | G12: 1868-732-4568 | H12: Small | I12: Swimming | J12: =IF(I12="Football","$120",IF(I12="Basketball","$200",IF(I12="Netball","$225",IF(I12="Hockey","$275",IF(I12="Swimming","$350"))))) -> $350 | K12: Installment | L12: =IF(K12="Full",J12*Dataset!$D$3*0.9,IF(K12="Installment",J12*Dataset!$D$3*1.15)) -> 3220
A13: Dorothy | B13: Caitlin | C13: Female | D13: Becky Dorothy | E13: =RANDBETWEEN(DATE(2007,1,1),DATE(2007,12,31)) -> 39108 | F13: Gaston Street ,Arouca,Trinidad and Tobago | G13: 1868-732-4569 | H13: Small | I13: Swimming | J13: =IF(I13="Football","$120",IF(I13="Basketball","$200",IF(I13="Netball","$225",IF(I13="Hockey","$275",IF(I13="Swimming","$350"))))) -> $350 | K13: Full | L13: =IF(K13="Full",J13*Dataset!$D$3*0.9,IF(K13="Installment",J13*Dataset!$D$3*1.15)) -> 2520
A14: Roxana | B14: Margarito | C14: Female | D14: Alana Roxana | E14: =RANDBETWEEN(DATE(2007,1,1),DATE(2007,12,31)) -> 39150 | F14: 100 Wrightson Rd. Port of Spain ,Arima,Trinidad and Tobago | G14: 1868-732-4570 | H14: Medium | I14: Swimming | J14: =IF(I14="Football","$120",IF(I14="Basketball","$200",IF(I14="Netball","$225",IF(I14="Hockey","$275",IF(I14="Swimming","$350"))))) -> $350 | K14: Installment | L14: =IF(K14="Full",J14*Dataset!$D$3*0.9,IF(K14="Installment",J14*Dataset!$D$3*1.15)) -> 3220
A15: Kaycee | B15: Stewart | C15: Male | D15: Kassidy Kaycee | E15: =RANDBETWEEN(DATE(2007,1,1),DATE(2007,12,31)) -> 39321 | F15: 3 Penitence St.,Arima,Trinidad and Tobago | G15: 1868-732-4571 | H15: Large | I15: Swimming | J15: =IF(I15="Football","$120",IF(I15="Basketball","$200",IF(I15="Netball","$225",IF(I15="Hockey","$275",IF(I15="Swimming","$350"))))) -> $350 | K15: Full | L15: =IF(K15="Full",J15*Dataset!$D$3*0.9,IF(K15="Installment",J15*Dataset!$D$3*1.15)) -> 2520
K16: Total | L16: =SUM(L3:L15) -> 38360
H17: Number of Campers | I17: =COUNTA(A3:A15) -> 13

Sheet Expenditure
A1: Expenditure
A2: Sport | B2: Number of Campers | C2: Food | D2: Drink | E2: Uniform | F2: Camp Counsellor | G2: Labour | H2: Bathrooms | I2: Security | J2: Total Costs(TT) | K2: Total Costs(US)
A3: =Dataset!B3 -> Football | B3: =Football!I20 -> 15 | C3: =Dataset!$G$3 -> 100 | D3: =Dataset!$H$3 -> 80 | E3: =Dataset!$I$3 -> 190 | F3: =Dataset!$J$3 -> 15 | G3: =Dataset!$K$3 -> 30 | H3: =Dataset!$L$3/5 -> 600 | I3: =Dataset!$M$3/5 -> 360 | J3: =SUM(C3:I3)*B3 -> 20625 | K3: =SUM(C3:I3)*B3/Dataset!$D$3 -> 2578.125
A4: =Dataset!B4 -> Basketball | B4: =Basketball!I19 -> 15 | C4: 100 | D4: =Dataset!$H$3 -> 80 | E4: =Dataset!$I$3 -> 190 | F4: =Dataset!$J$3 -> 15 | G4: =Dataset!$K$3 -> 30 | H4: =Dataset!$L$3/5 -> 600 | I4: =Dataset!$M$3/5 -> 360 | J4: =SUM(C4:I4)*B4 -> 20625 | K4: =SUM(C4:I4)*B4/Dataset!$D$3 -> 2578.125
A5: =Dataset!B5 -> Netball | B5: =Netball!I17 -> 13 | C5: 100 | D5: =Dataset!$H$3 -> 80 | E5: =Dataset!$I$3 -> 190 | F5: =Dataset!$J$3 -> 15 | G5: =Dataset!$K$3 -> 30 | H5: =Dataset!$L$3/5 -> 600 | I5: =Dataset!$M$3/5 -> 360 | J5: =SUM(C5:I5)*B5 -> 17875 | K5: =SUM(C5:I5)*B5/Dataset!$D$3 -> 2234.375
A6: =Dataset!B6 -> Hockey | B6: =Hockey!I16 -> 12 | C6: 100 | D6: =Dataset!$H$3 -> 80 | E6: =Dataset!$I$3 -> 190 | F6: =Dataset!$J$3 -> 15 | G6: =Dataset!$K$3 -> 30 | H6: =Dataset!$L$3/5 -> 600 | I6: =Dataset!$M$3/5 -> 360 | J6: =SUM(C6:I6)*B6 -> 16500 | K6: =SUM(C6:I6)*B6/Dataset!$D$3 -> 2062.5
A7: =Dataset!B7 -> Swimming | B7: =Swimming!I17 -> 13 | C7: 100 | D7: =Dataset!$H$3 -> 80 | E7: =Dataset!$I$3 -> 190 | F7: =Dataset!$J$3 -> 15 | G7: =Dataset!$K$3 -> 30 | H7: =Dataset!$L$3/5 -> 600 | I7: =Dataset!$M$3/5 -> 360 | J7: =SUM(C7:I7)*B7 -> 17875 | K7: =SUM(C7:I7)*B7/Dataset!$D$3 -> 2234.375
I8: Total Expenditure | J8: =SUM(J3:J7) -> 93500 | K8: =SUM(K3:K7) -> 11687.5

Sheet Simple Filter
A1: Simple Filter-Football
A3: Surname | B3: First Name | C3: Gender | D3: Parent's Name | E3: Date of Birth (dd/mm/yr) | F3: Address | G3: Contact Information | H3: Uniform Size | I3: Sport | J3: Registration Cost(US) | K3: Method Of Payment | L3: Grand Total(TT)
A4: Best | B4: Pauline | C4: Female | D4: Carl Best | E4: =RANDBETWEEN(DATE(2007,1,1),DATE(2007,12,31)) -> 39395 | F4: 9776 Birchpond St. | G4: 1868-745-0923 | H4: Small | I4: Football | J4: =IF(I4="Football","$120",IF(I4="Basketball","$200",IF(I4="Netball","$225",IF(I4="Hockey","$275",IF(I4="Swimming","$350"))))) -> $120 | K4: Full | L4: =IF(K4="Full",J4*Dataset!$D$3*0.9,IF(K4="Installment",J4*Dataset!$D$3*1.15)) -> 864
A5: Alvarado | B5: Elroy | C5: Male | D5: Michelle Alvarado | E5: =RANDBETWEEN(DATE(2007,1,1),DATE(2007,12,31)) -> 39369 | F5: Stone & Charles Sts., Port of Spain | G5: 1868-236-7908 | H5: Large | I5: Football | J5: =IF(I5="Football","$120",IF(I5="Basketball","$200",IF(I5="Netball","$225",IF(I5="Hockey","$275",IF(I5="Swimming","$350"))))) -> $120 | K5: Full | L5: =IF(K5="Full",J5*Dataset!$D$3*0.9,IF(K5="Installment",J5*Dataset!$D$3*1.15)) -> 864
A6: Franklin | B6: Aurora | C6: Female | D6: Kyle Aurora | E6: =RANDBETWEEN(DATE(2007,1,1),DATE(2007,12,31)) -> 39363 | F6: 19 Mucurapo Road | G6: 1868-345-9453 | H6: Large | I6: Football | J6: =IF(I6="Football","$120",IF(I6="Basketball","$200",IF(I6="Netball","$225",IF(I6="Hockey","$275",IF(I6="Swimming","$350"))))) -> $120 | K6: Installment | L6: =IF(K6="Full",J6*Dataset!$D$3*0.9,IF(K6="Installment",J6*Dataset!$D$3*1.15)) -> 1104
A7: Maharaj | B7: Kaitlyn | C7: Female | D7: Jeremy Maharaj | E7: =RANDBETWEEN(DATE(2007,1,1),DATE(2007,12,31)) -> 39113 | F7: Constance Street | G7: 1868-224-8843 | H7: Medium | I7: Football | J7: =IF(I7="Football","$120",IF(I7="Basketball","$200",IF(I7="Netball","$225",IF(I7="Hockey","$275",IF(I7="Swimming","$350"))))) -> $120 | K7: Installment | L7: =IF(K7="Full",J7*Dataset!$D$3*0.9,IF(K7="Installment",J7*Dataset!$D$3*1.15)) -> 1104
A8: Moses | B8: Maurice | C8: Female | D8: Andrea Moses | E8: =RANDBETWEEN(DATE(2007,1,1),DATE(2007,12,31)) -> 39219 | F8: 102 Nolan Street | G8: 1868-456-3722 | H8: Small | I8: Football | J8: =IF(I8="Football","$120",IF(I8="Basketball","$200",IF(I8="Netball","$225",IF(I8="Hockey","$275",IF(I8="Swimming","$350"))))) -> $120 | K8: Full | L8: =IF(K8="Full",J8*Dataset!$D$3*0.9,IF(K8="Installment",J8*Dataset!$D$3*1.15)) -> 864
A9: Jamieson | B9: Richard | C9: Male | D9: Daisy Jamieson | E9: =RANDBETWEEN(DATE(2007,1,1),DATE(2007,12,31)) -> 39147 | F9: Milford Road, Milford | G9: 1868-745-9021 | H9: Medium | I9: Football | J9: =IF(I9="Football","$120",IF(I9="Basketball","$200",IF(I9="Netball","$225",IF(I9="Hockey","$275",IF(I9="Swimming","$350"))))) -> $120 | K9: Full | L9: =IF(K9="Full",J9*Dataset!$D$3*0.9,IF(K9="Installment",J9*Dataset!$D$3*1.15)) -> 864
A10: Jamieson | B10: Mark | C10: Male | D10: Daisy Jamieson | E10: =RANDBETWEEN(DATE(2007,1,1),DATE(2007,12,31)) -> 39282 | F10: Milford Road, Milford | G10: 1868-745-9021 | H10: Medium | I10: Football | J10: =IF(I10="Football","$120",IF(I10="Basketball","$200",IF(I10="Netball","$225",IF(I10="Hockey","$275",IF(I10="Swimming","$350"))))) -> $120 | K10: Full | L10: =IF(K10="Full",J10*Dataset!$D$3*0.9,IF(K10="Installment",J10*Dataset!$D$3*1.15)) -> 864
A11: Ramousar | B11: Nathan | C11: Male | D11: Cary Ramousar | E11: =RANDBETWEEN(DATE(2007,1,1),DATE(2007,12,31)) -> 39329 | F11: 34 Carrington Street | G11: 1868-223-0012 | H11: Small | I11: Football | J11: =IF(I11="Football","$120",IF(I11="Basketball","$200",IF(I11="Netball","$225",IF(I11="Hockey","$275",IF(I11="Swimming","$350"))))) -> $120 | K11: Installment | L11: =IF(K11="Full",J11*Dataset!$D$3*0.9,IF(K11="Installment",J11*Dataset!$D$3*1.15)) -> 1104
A12: Joseph | B12: Peter | C12: Male | D12: Michael Joseph | E12: =RANDBETWEEN(DATE(2007,1,1),DATE(2007,12,31)) -> 39410 | F12: 135 John Street | G12: 1868-432-4567 | H12: Large | I12: Football | J12: =IF(I12="Football","$120",IF(I12="Basketball","$200",IF(I12="Netball","$225",IF(I12="Hockey","$275",IF(I12="Swimming","$350"))))) -> $120 | K12: Installment | L12: =IF(K12="Full",J12*Dataset!$D$3*0.9,IF(K12="Installment",J12*Dataset!$D$3*1.15)) -> 1104
A13: Rosa | B13: Susan | C13: Female | D13: Natasha Rosa | E13: =RANDBETWEEN(DATE(2007,1,1),DATE(2007,12,31)) -> 39245 | F13: 22 Penco Street | G13: 1868-275-9743 | H13: Medium | I13: Football | J13: =IF(I13="Football","$120",IF(I13="Basketball","$200",IF(I13="Netball","$225",IF(I13="Hockey","$275",IF(I13="Swimming","$350"))))) -> $120 | K13: Full | L13: =IF(K13="Full",J13*Dataset!$D$3*0.9,IF(K13="Installment",J13*Dataset!$D$3*1.15)) -> 864
A14: Sharma | B14: Andrea | C14: Female | D14: Alex Sharma | E14: =RANDBETWEEN(DATE(2007,1,1),DATE(2007,12,31)) -> 39315 | F14: #49 Thompson Street | G14: 1868-349-9732 | H14: Samll | I14: Football | J14: =IF(I14="Football","$120",IF(I14="Basketball","$200",IF(I14="Netball","$225",IF(I14="Hockey","$275",IF(I14="Swimming","$350"))))) -> $120 | K14: Installment | L14: =IF(K14="Full",J14*Dataset!$D$3*0.9,IF(K14="Installment",J14*Dataset!$D$3*1.15)) -> 1104
A15: Davinson | B15: Stuart | C15: Male | D15: Vanessa Davinson | E15: =RANDBETWEEN(DATE(2007,1,1),DATE(2007,12,31)) -> 39356 | F15: Fourth Street, P.O.Box 4300 | G15: 1868-754-0372 | H15: Medium | I15: Football | J15: =IF(I15="Football","$120",IF(I15="Basketball","$200",IF(I15="Netball","$225",IF(I15="Hockey","$275",IF(I15="Swimming","$350"))))) -> $120 | K15: Full | L15: =IF(K15="Full",J15*Dataset!$D$3*0.9,IF(K15="Installment",J15*Dataset!$D$3*1.15)) -> 864
... A18: Serelo | B18: David | C18: Male | D18: Kevin Serelo | E18: =RANDBETWEEN(DATE(2007,1,1),DATE(2007,12,31)) -> 39346 | F18: 15 Woodpecker Lane, P.O.Box 23700 | G18: 1868-321-7832 | H18: Large | I18: Football | J18: =IF(I18="Football","$120",IF(I18="Basketball","$200",IF(I18="Netball","$225",IF(I18="Hockey","$275",IF(I18="Swimming","$350"))))) -> $120 | K18: Full | L18: =IF(K18="Full",J18*Dataset!$D$3*0.9,IF(K18="Installment",J18*Dataset!$D$3*1.15)) -> 864
K19: Total | L19: =SUM(L4:L18) -> 14400
H20: Number of Campers | I20: =COUNTA(A4:A18) -> 15

Sheet Pivot Table
A1: Pivot Table
A3: Football Sum of Grand Total(TT)
A4: 14400
A6: Basketball Sum of Grand Total(TT)
A7: 24000
A9: Netball Sum of Grand Total(TT)
A10: 23310
A12: Hockey Sum of Grand Total(TT)
A13: 27060
A15: Swimming Sum of Grand Total(TT)
A16: 38360

Sheet Advance Filter
A1: Advance Filter- Football
A3: Surname | B3: First Name | C3: Gender | D3: Parent's Name | E3: Date of Birth (dd/mm/yr) | F3: Address | G3: Contact Information | H3: Uniform Size | I3: Sport | J3: Registration Cost(US) | K3: Method Of Payment | L3: Grand Total(TT)
A4: Best | B4: Pauline | C4: Female | D4: Carl Best | E4: =RANDBETWEEN(DATE(2007,1,1),DATE(2007,12,31)) -> 39391 | F4: 9776 Birchpond St. | G4: 1868-745-0923 | H4: Small | I4: Football | J4: =IF(I4="Football","$120",IF(I4="Basketball","$200",IF(I4="Netball","$225",IF(I4="Hockey","$275",IF(I4="Swimming","$350"))))) -> $120 | K4: Full | L4: =IF(K4="Full",J4*Dataset!$D$3*0.9,IF(K4="Installment",J4*Dataset!$D$3*1.15)) -> 864
A5: Alvarado | B5: Elroy | C5: Male | D5: Michelle Alvarado | E5: =RANDBETWEEN(DATE(2007,1,1),DATE(2007,12,31)) -> 39416 | F5: Stone & Charles Sts., Port of Spain | G5: 1868-236-7908 | H5: Large | I5: Football | J5: =IF(I5="Football","$120",IF(I5="Basketball","$200",IF(I5="Netball","$225",IF(I5="Hockey","$275",IF(I5="Swimming","$350"))))) -> $120 | K5: Full | L5: =IF(K5="Full",J5*Dataset!$D$3*0.9,IF(K5="Installment",J5*Dataset!$D$3*1.15)) -> 864
A6: Franklin | B6: Aurora | C6: Female | D6: Kyle Aurora | E6: =RANDBETWEEN(DATE(2007,1,1),DATE(2007,12,31)) -> 39441 | F6: 19 Mucurapo Road | G6: 1868-345-9453 | H6: Large | I6: Football | J6: =IF(I6="Football","$120",IF(I6="Basketball","$200",IF(I6="Netball","$225",IF(I6="Hockey","$275",IF(I6="Swimming","$350"))))) -> $120 | K6: Installment | L6: =IF(K6="Full",J6*Dataset!$D$3*0.9,IF(K6="Installment",J6*Dataset!$D$3*1.15)) -> 1104
A7: Maharaj | B7: Kaitlyn | C7: Female | D7: Jeremy Maharaj | E7: =RANDBETWEEN(DATE(2007,1,1),DATE(2007,12,31)) -> 39348 | F7: Constance Street | G7: 1868-224-8843 | H7: Medium | I7: Football | J7: =IF(I7="Football","$120",IF(I7="Basketball","$200",IF(I7="Netball","$225",IF(I7="Hockey","$275",IF(I7="Swimming","$350"))))) -> $120 | K7: Installment | L7: =IF(K7="Full",J7*Dataset!$D$3*0.9,IF(K7="Installment",J7*Dataset!$D$3*1.15)) -> 1104
A8: Moses | B8: Maurice | C8: Female | D8: Andrea Moses | E8: =RANDBETWEEN(DATE(2007,1,1),DATE(2007,12,31)) -> 39119 | F8: 102 Nolan Street | G8: 1868-456-3722 | H8: Small | I8: Football | J8: =IF(I8="Football","$120",IF(I8="Basketball","$200",IF(I8="Netball","$225",IF(I8="Hockey","$275",IF(I8="Swimming","$350"))))) -> $120 | K8: Full | L8: =IF(K8="Full",J8*Dataset!$D$3*0.9,IF(K8="Installment",J8*Dataset!$D$3*1.15)) -> 864
A9: Jamieson | B9: Richard | C9: Male | D9: Daisy Jamieson | E9: =RANDBETWEEN(DATE(2007,1,1),DATE(2007,12,31)) -> 39424 | F9: Milford Road, Milford | G9: 1868-745-9021 | H9: Medium | I9: Football | J9: =IF(I9="Football","$120",IF(I9="Basketball","$200",IF(I9="Netball","$225",IF(I9="Hockey","$275",IF(I9="Swimming","$350"))))) -> $120 | K9: Full | L9: =IF(K9="Full",J9*Dataset!$D$3*0.9,IF(K9="Installment",J9*Dataset!$D$3*1.15)) -> 864
A10: Jamieson | B10: Mark | C10: Male | D10: Daisy Jamieson | E10: =RANDBETWEEN(DATE(2007,1,1),DATE(2007,12,31)) -> 39166 | F10: Milford Road, Milford | G10: 1868-745-9021 | H10: Medium | I10: Football | J10: =IF(I10="Football","$120",IF(I10="Basketball","$200",IF(I10="Netball","$225",IF(I10="Hockey","$275",IF(I10="Swimming","$350"))))) -> $120 | K10: Full | L10: =IF(K10="Full",J10*Dataset!$D$3*0.9,IF(K10="Installment",J10*Dataset!$D$3*1.15)) -> 864
A11: Ramousar | B11: Nathan | C11: Male | D11: Cary Ramousar | E11: =RANDBETWEEN(DATE(2007,1,1),DATE(2007,12,31)) -> 39204 | F11: 34 Carrington Street | G11: 1868-223-0012 | H11: Small | I11: Football | J11: =IF(I11="Football","$120",IF(I11="Basketball","$200",IF(I11="Netball","$225",IF(I11="Hockey","$275",IF(I11="Swimming","$350"))))) -> $120 | K11: Installment | L11: =IF(K11="Full",J11*Dataset!$D$3*0.9,IF(K11="Installment",J11*Dataset!$D$3*1.15)) -> 1104
A12: Joseph | B12: Peter | C12: Male | D12: Michael Joseph | E12: =RANDBETWEEN(DATE(2007,1,1),DATE(2007,12,31)) -> 39183 | F12: 135 John Street | G12: 1868-432-4567 | H12: Large | I12: Football | J12: =IF(I12="Football","$120",IF(I12="Basketball","$200",IF(I12="Netball","$225",IF(I12="Hockey","$275",IF(I12="Swimming","$350"))))) -> $120 | K12: Installment | L12: =IF(K12="Full",J12*Dataset!$D$3*0.9,IF(K12="Installment",J12*Dataset!$D$3*1.15)) -> 1104
A13: Rosa | B13: Susan | C13: Female | D13: Natasha Rosa | E13: =RANDBETWEEN(DATE(2007,1,1),DATE(2007,12,31)) -> 39200 | F13: 22 Penco Street | G13: 1868-275-9743 | H13: Medium | I13: Football | J13: =IF(I13="Football","$120",IF(I13="Basketball","$200",IF(I13="Netball","$225",IF(I13="Hockey","$275",IF(I13="Swimming","$350"))))) -> $120 | K13: Full | L13: =IF(K13="Full",J13*Dataset!$D$3*0.9,IF(K13="Installment",J13*Dataset!$D$3*1.15)) -> 864
A14: Sharma | B14: Andrea | C14: Female | D14: Alex Sharma | E14: =RANDBETWEEN(DATE(2007,1,1),DATE(2007,12,31)) -> 39218 | F14: #49 Thompson Street | G14: 1868-349-9732 | H14: Samll | I14: Football | J14: =IF(I14="Football","$120",IF(I14="Basketball","$200",IF(I14="Netball","$225",IF(I14="Hockey","$275",IF(I14="Swimming","$350"))))) -> $120 | K14: Installment | L14: =IF(K14="Full",J14*Dataset!$D$3*0.9,IF(K14="Installment",J14*Dataset!$D$3*1.15)) -> 1104
A15: Davinson | B15: Stuart | C15: Male | D15: Vanessa Davinson | E15: =RANDBETWEEN(DATE(2007,1,1),DATE(2007,12,31)) -> 39380 | F15: Fourth Street, P.O.Box 4300 | G15: 1868-754-0372 | H15: Medium | I15: Football | J15: =IF(I15="Football","$120",IF(I15="Basketball","$200",IF(I15="Netball","$225",IF(I15="Hockey","$275",IF(I15="Swimming","$350"))))) -> $120 | K15: Full | L15: =IF(K15="Full",J15*Dataset!$D$3*0.9,IF(K15="Installment",J15*Dataset!$D$3*1.15)) -> 864
... A18: Serelo | B18: David | C18: Male | D18: Kevin Serelo | E18: =RANDBETWEEN(DATE(2007,1,1),DATE(2007,12,31)) -> 39120 | F18: 15 Woodpecker Lane, P.O.Box 23700 | G18: 1868-321-7832 | H18: Large | I18: Football | J18: =IF(I18="Football","$120",IF(I18="Basketball","$200",IF(I18="Netball","$225",IF(I18="Hockey","$275",IF(I18="Swimming","$350"))))) -> $120 | K18: Full | L18: =IF(K18="Full",J18*Dataset!$D$3*0.9,IF(K18="Installment",J18*Dataset!$D$3*1.15)) -> 864
K19: Total | L19: =SUM(L4:L18) -> 14400
H20: Number of Campers | I20: =COUNTA(A4:A18) -> 15
D23: =$K$3 -> Method Of Payment
D24: Full
A25: Surname | B25: First Name | C25: Gender | D25: Parent's Name | E25: Date of Birth (dd/mm/yr) | F25: Address | G25: Contact Information | H25: Uniform Size | I25: Sport | J25: Registration Cost(US) | K25: Method Of Payment | L25: Grand Total(TT)
A26: Best | B26: Pauline | C26: Female | D26: Carl Best | E26: 39124 | F26: 9776 Birchpond St. | G26: 1868-745-0923 | H26: Small | I26: Football | J26: $120 | K26: Full | L26: 864
A27: Alvarado | B27: Elroy | C27: Male | D27: Michelle Alvarado | E27: 39141 | F27: Stone & Charles Sts., Port of Spain | G27: 1868-236-7908 | H27: Large | I27: Football | J27: $120 | K27: Full | L27: 864
A28: Moses | B28: Maurice | C28: Female | D28: Andrea Moses | E28: 39420 | F28: 102 Nolan Street | G28: 1868-456-3722 | H28: Small | I28: Football | J28: $120 | K28: Full | L28: 864
A29: Jamieson | B29: Richard | C29: Male | D29: Daisy Jamieson | E29: 39363 | F29: Milford Road, Milford | G29: 1868-745-9021 | H29: Medium | I29: Football | J29: $120 | K29: Full | L29: 864
A30: Jamieson | B30: Mark | C30: Male | D30: Daisy Jamieson | E30: 39388 | F30: Milford Road, Milford | G30: 1868-745-9021 | H30: Medium | I30: Football | J30: $120 | K30: Full | L30: 864
A31: Rosa | B31: Susan | C31: Female | D31: Natasha Rosa | E31: 39289 | F31: 22 Penco Street | G31: 1868-275-9743 | H31: Medium | I31: Football | J31: $120 | K31: Full | L31: 864
A32: Davinson | B32: Stuart | C32: Male | D32: Vanessa Davinson | E32: 39385 | F32: Fourth Street, P.O.Box 4300 | G32: 1868-754-0372 | H32: Medium | I32: Football | J32: $120 | K32: Full | L32: 864
A33: Leslie | B33: Kimberly | C33: Female | D33: Marie Leslie | E33: 39104 | F33: Edinburgh Village, P.O.Box 33400 | G33: 1868-632-6732 | H33: Medium | I33: Football | J33: $120 | K33: Full | L33: 864
A34: Serelo | B34: David | C34: Male | D34: Kevin Serelo | E34: 39209 | F34: 15 Woodpecker Lane, P.O.Box 23700 | G34: 1868-321-7832 | H34: Large | I34: Football | J34: $120 | K34: Full | L34: 864

Sheet Income VS Expenditure
A1: Income VS Expenditure
B2: Income(TT) | C2: Expenditure(TT)
A3: =Dataset!B3 -> Football | B3: =GETPIVOTDATA("Grand Total(TT)",'Pivot Table'!$A$3) -> 14400 | C3: =Expenditure!J3 -> 20625
A4: =Dataset!B4 -> Basketball | B4: =GETPIVOTDATA("Grand Total(TT)",'Pivot Table'!$A$6) -> 24000 | C4: =Expenditure!J4 -> 20625
A5: =Dataset!B5 -> Netball | B5: =GETPIVOTDATA("Grand Total(TT)",'Pivot Table'!$A$9) -> 23310 | C5: =Expenditure!J5 -> 17875
A6: =Dataset!B6 -> Hockey | B6: =GETPIVOTDATA("Grand Total(TT)",'Pivot Table'!$A$12) -> 27060 | C6: =Expenditure!J6 -> 16500
A7: =Dataset!B7 -> Swimming | B7: =GETPIVOTDATA("Grand Total(TT)",'Pivot Table'!$A$15) -> 38360 | C7: =Expenditure!J7 -> 17875

Sheet Dataset
A1: Dataset
A2: Gender | B2: Sport | C2: Uniform Size | D2: Conversion Rate | E2: Payment method | F2: Type of payment | G2: Food | H2: Drink | I2: Uniform | J2: Camp Counsellor | K2: Labour | L2: Bathrooms | M2: Security
A3: Male | B3: Football | C3: Small | D3: 8 | E3: Full | F3: Discount 10% | G3: 100 | H3: 80 | I3: 190 | J3: 15 | K3: 30 | L3: 3000 | M3: 1800
A4: Female | B4: Basketball | C4: Medium | E4: Installment | F4: Interest 15%
B5: Netball | C5: Large
B6: Hockey
B7: Swimming
